devfacPyLogger/__init__.py
devfac_py_logger-0.2.2.dist-info/LICENSE
devfac_py_logger-0.2.2.dist-info/METADATA
devfac_py_logger-0.2.2.dist-info/WHEEL
devfac_py_logger-0.2.2.dist-info/top_level.txt
devfac_py_logger-0.2.2.dist-info/RECORD
