Metadata-Version: 2.1
Name: devfac-py-logger
Version: 0.2.2
Summary: Simple, Colored, File and Line number printable logger
Home-page: https://github.com/transpine/devfac-py-logger
Author: transpine
Author-email: transpine@gmail.com
License: MIT
Platform: UNKNOWN
Classifier: Programming Language :: Python :: 3
Classifier: License :: OSI Approved :: MIT License
Classifier: Operating System :: OS Independent
Requires-Python: >=3
Requires-Dist: colorlog
Requires-Dist: ipython
